bitcoin_explorer-1.2.21.dist-info/METADATA
bitcoin_explorer-1.2.21.dist-info/WHEEL
bitcoin_explorer-1.2.21.dist-info/license_files/LICENSE.txt
bitcoin_explorer/__init__.py
bitcoin_explorer/bitcoin_explorer.cpython-38-x86_64-linux-gnu.so
bitcoin_explorer-1.2.21.dist-info/RECORD
