Metadata-Version: 2.1
Name: bitcoin-explorer
Version: 1.2.21
Classifier: Programming Language :: Rust
Classifier: License :: OSI Approved :: MIT License
Classifier: Intended Audience :: Science/Research
Classifier: Operating System :: MacOS :: MacOS X
Classifier: Operating System :: Microsoft :: Windows
Classifier: Operating System :: POSIX :: Linux
Classifier: Programming Language :: Python :: 3.6
Classifier: Programming Language :: Python :: 3.7
Classifier: Programming Language :: Python :: 3.8
Classifier: Programming Language :: Python :: 3.9
Classifier: Programming Language :: Python :: 3.10
License-File: LICENSE.txt
Summary: High Performance Blockchain Deserializer
Keywords: rust,bitcoin,blockchain,deserialize,parser,explorer,crypto,transaction
Home-Page: https://github.com/Congyuwang/Py-Bitcoin-Explorer
Project-URL: Source Code, https://github.com/Congyuwang/Py-Bitcoin-Explorer
